xu60/__init__.py
xu60/__main__.py
xu60/data.py
xu60/main.py
xu60-0.1.4.dist-info/METADATA
xu60-0.1.4.dist-info/WHEEL
xu60-0.1.4.dist-info/licenses/LICENSE
xu60-0.1.4.dist-info/RECORD
