Metadata-Version: 2.4
Name: xu60
Version: 0.1.4
Summary: needed now more than ever
Project-URL: Repository, https://github.com/rfinz/xu60.git
Author-email: Raymond Finzel <github@rfinz.mozmail.com>
License-Expression: GPL-3.0-or-later
License-File: LICENSE
Keywords: api,content addressing,hypertext,versioning,web
Classifier: Development Status :: 2 - Pre-Alpha
Classifier: Environment :: Web Environment
Classifier: Intended Audience :: Developers
Classifier: Intended Audience :: Other Audience
Classifier: License :: OSI Approved :: GNU General Public License v3 or later (GPLv3+)
Classifier: Operating System :: OS Independent
Classifier: Programming Language :: Python :: 3
Classifier: Topic :: Artistic Software
Classifier: Topic :: Internet
Classifier: Topic :: Software Development :: Version Control
Requires-Python: >=3.11
Requires-Dist: pygit2~=1.19.0
Requires-Dist: starlette~=0.50.0
Provides-Extra: server
Requires-Dist: uvicorn; extra == 'server'
